{
  "stevilka": "HCY-20866449",
  "datum_izdaje": "2026-01-13",
  "datum_zapadlosti": "",
  "datum_storitve_od": "2026-01-13",
  "datum_storitve_do": "2030-04-13",
  "znesek_skupaj": 116.53,
  "znesek_ddv": 21.01,
  "znesek_brez_ddv": 95.52,
  "partner": {
    "naziv": "Hostinger International Ltd.",
    "davcna_stevilka": "CY10301365E"
  },
  "postavke": [
    {
      "opis": "Premium Web Hosting (billed every 4 years)",
      "kolicina": 1.0,
      "enota_mere": "kos",
      "cena_enote": 527.52,
      "popust": 0.0,
      "stopnja_ddv": 22.0,
      "znesek_skupaj": 116.53
    }
  ]
}